<!DOCTYPE codename-engine-character>
<character x="0" icon="gen-bf-IVAN" camx="0" y="0" isGF="false" camy="-110" flipX="true" isPlayer="true" sprite="gen bf" color="#000000" gameOverChar="gen-bf-dead">
	<anim x="0" loop="false" y="0" fps="30" anim="Anims/Phase 3/Idle" name="idle"/>
	<anim x="0" loop="false" y="0" fps="30" anim="Anims/Phase 3/Down" name="singDOWN"/>
	<anim x="0" loop="false" y="0" fps="30" anim="Anims/Phase 3/Miss Down" name="singDOWNmiss"/>
	<anim x="0" loop="false" y="0" fps="30" anim="Anims/Phase 3/Miss Right" name="singRIGHTmiss"/>
	<anim x="0" loop="false" y="0" fps="30" anim="Anims/Phase 3/Miss Left" name="singLEFTmiss"/>
	<anim x="0" loop="false" y="0" fps="30" anim="Anims/Phase 3/Left" name="singLEFT"/>
	<anim x="0" loop="false" y="0" fps="30" anim="Anims/Phase 3/Up" name="singUP"/>
	<anim x="0" loop="false" y="0" fps="30" anim="Anims/Phase 3/Right" name="singRIGHT"/>
	<anim x="0" loop="false" y="0" fps="30" anim="Anims/Phase 3/Miss Up" name="singUPmiss"/>
</character>
